thermalprinter/__init__.py
thermalprinter/constants.py
thermalprinter/exceptions.py
thermalprinter/gnu.png
thermalprinter/py.typed
thermalprinter/thermalprinter.py
thermalprinter/tools.py
thermalprinter/recipes/__init__.py
thermalprinter/recipes/calendar/__init__.py
thermalprinter/recipes/calendar/__main__.py
thermalprinter/recipes/persian/__init__.py
thermalprinter/recipes/weather/__init__.py
thermalprinter/recipes/weather/__main__.py
thermalprinter/recipes/weather/saints.lst
thermalprinter-2.1.0.dist-info/METADATA
thermalprinter-2.1.0.dist-info/WHEEL
thermalprinter-2.1.0.dist-info/entry_points.txt
thermalprinter-2.1.0.dist-info/licenses/LICENSE
thermalprinter-2.1.0.dist-info/RECORD
